[{"event": 60, "level": 141.25, "heal": 28.787432604733418, "op_lvl": 9.0, "dead": -2.5, "badge": 25, "explore": 401.01250000000005}, {"event": 60, "level": 126.25, "heal": 54.42343921865795, "op_lvl": 9.0, "dead": -3.5, "badge": 25, "explore": 412.825}, {"event": 60, "level": 128.75, "heal": 36.99534307201263, "op_lvl": 9.0, "dead": -3.5, "badge": 25, "explore": 387.01250000000005}, {"event": 65, "level": 118.75, "heal": 39.39787266995622, "op_lvl": 9.0, "dead": -3.0, "badge": 25, "explore": 400.57500000000005}]