[{"event": 70, "level": 123.75, "heal": 31.30837217189339, "op_lvl": 9.0, "dead": -2.0, "badge": 25, "explore": 399.87500000000006}, {"event": 65, "level": 116.25, "heal": 64.39778327729903, "op_lvl": 9.0, "dead": -2.5, "badge": 25, "explore": 418.6}, {"event": 65, "level": 125.0, "heal": 44.51391153593907, "op_lvl": 9.0, "dead": -2.5, "badge": 25, "explore": 414.92500000000007}, {"event": 75, "level": 127.5, "heal": 59.13436114748119, "op_lvl": 9.0, "dead": -3.0, "badge": 25, "explore": 415.88750000000005}]